moduleZoo/__init__.py
moduleZoo/attention/__init__.py
moduleZoo/attention/conv_multi_head_attention.py
moduleZoo/attention/conv_self_attention.py
moduleZoo/attention/linear_multi_head_attention.py
moduleZoo/attention/utils.py
moduleZoo/convolution/__init__.py
moduleZoo/convolution/convblocks.py
moduleZoo/convolution/invertedconvblocks.py
moduleZoo/dense/__init__.py
moduleZoo/dense/denseblocks.py
moduleZoo/extensions/__init__.py
moduleZoo/extensions/conv2d.py
moduleZoo/graphs/__init__.py
moduleZoo/graphs/attention/__init__.py
moduleZoo/graphs/attention/graph_linear_multi_head_attention.py
moduleZoo/graphs/graph_conv.py
moduleZoo/graphs/utils.py
moduleZoo/resblocks/__init__.py
moduleZoo/resblocks/bottleneckresidual.py
moduleZoo/resblocks/invertedresidual.py
moduleZoo/resblocks/residual.py
moduleZoo/utils.py
mzLosses/contrastive.py
mzt-2.0.0.dist-info/METADATA
mzt-2.0.0.dist-info/WHEEL
mzt-2.0.0.dist-info/entry_points.txt
mzt-2.0.0.dist-info/licenses/LICENSE
mzt-2.0.0.dist-info/RECORD
